setup.py
src/tiberium/__init__.py
src/tiberium.egg-info/PKG-INFO
src/tiberium.egg-info/SOURCES.txt
src/tiberium.egg-info/dependency_links.txt
src/tiberium.egg-info/entry_points.txt
src/tiberium.egg-info/top_level.txt
src/tiberium.egg-info/zip-safe
src/tiberium/base/__init__.py
src/tiberium/base/api.py
src/tiberium/base/common.py
src/tiberium/base/format.py
src/tiberium/base/repo.py
src/tiberium/utils/__init__.py
src/tiberium/utils/http.py
src/tiberium/utils/path.py
src/tiberium/utils/shell.py