Metadata-Version: 1.1
Name: tiberium
Version: 0.2.3
Summary: Tiberium System
Home-page: http://tiberium.com
Author: Hive Solutions Lda.
Author-email: development@hive.pt
License: GNU General Public License (GPL), Version 3
Keywords: tiberium platform service
Platform: UNKNOWN
Classifier: Development Status :: 3 - Alpha
Classifier: Topic :: Utilities
Classifier: License :: OSI Approved :: GNU General Public License (GPL)
Classifier: Operating System :: OS Independent
Classifier: Programming Language :: Python
Classifier: Programming Language :: Python :: 2.6
Classifier: Programming Language :: Python :: 2.7
